MANIFEST.in
setup.py
src/twitter/__init__.py
src/twitter.common.pants.egg-info/PKG-INFO
src/twitter.common.pants.egg-info/SOURCES.txt
src/twitter.common.pants.egg-info/dependency_links.txt
src/twitter.common.pants.egg-info/namespace_packages.txt
src/twitter.common.pants.egg-info/requires.txt
src/twitter.common.pants.egg-info/top_level.txt
src/twitter.common.pants.egg-info/zip-safe
src/twitter/common/__init__.py
src/twitter/common/pants/__init__.py
src/twitter/common/pants/jvm/__init__.py
src/twitter/common/pants/jvm/args/__init__.py
src/twitter/common/pants/jvm/args/register.py
src/twitter/common/pants/jvm/args/tasks/__init__.py
src/twitter/common/pants/jvm/args/tasks/resource_mapper.py