Metadata-Version: 1.1
Name: twitter.common.pants
Version: 0.8.0
Summary: twitter.common plugins for the pants build system.
Home-page: https://github.com/twitter/commons
Author: UNKNOWN
Author-email: UNKNOWN
License: Apache License, Version 2.0
Platform: UNKNOWN
Classifier: Intended Audience :: Developers
Classifier: License :: OSI Approved :: Apache Software License
Classifier: Operating System :: OS Independent
Classifier: Programming Language :: Python
